kdaquila_structure_lint/__init__.py
kdaquila_structure_lint/cli/__init__.py
kdaquila_structure_lint/cli/_functions/__init__.py
kdaquila_structure_lint/cli/_functions/main.py
kdaquila_structure_lint/cli/_tests/__init__.py
kdaquila_structure_lint/cli/_tests/test_cli_argument_parsing.py
kdaquila_structure_lint/cli/_tests/test_cli_exit_codes.py
kdaquila_structure_lint/cli/_tests/test_cli_integration_paths.py
kdaquila_structure_lint/cli/_tests/test_cli_integration_validators.py
kdaquila_structure_lint/config/__init__.py
kdaquila_structure_lint/config/_constants/__init__.py
kdaquila_structure_lint/config/_constants/defaults.py
kdaquila_structure_lint/config/_functions/__init__.py
kdaquila_structure_lint/config/_functions/find_project_root.py
kdaquila_structure_lint/config/_functions/load_config.py
kdaquila_structure_lint/config/_tests/__init__.py
kdaquila_structure_lint/config/_tests/test_config_dataclasses.py
kdaquila_structure_lint/config/_tests/test_find_project_root.py
kdaquila_structure_lint/config/_tests/test_load_config_custom.py
kdaquila_structure_lint/config/_tests/test_load_config_defaults.py
kdaquila_structure_lint/config/_tests/test_load_config_paths.py
kdaquila_structure_lint/config/_types/__init__.py
kdaquila_structure_lint/config/_types/config.py
kdaquila_structure_lint/definition_counter/__init__.py
kdaquila_structure_lint/definition_counter/_functions/count_python_definitions.py
kdaquila_structure_lint/definition_counter/_functions/count_top_level_definitions.py
kdaquila_structure_lint/definition_counter/_functions/detect_extra_definitions.py
kdaquila_structure_lint/definition_counter/_functions/detect_python_extra_definitions.py
kdaquila_structure_lint/definition_counter/_functions/get_assigned_names.py
kdaquila_structure_lint/definition_counter/_functions/is_dunder_name.py
kdaquila_structure_lint/definition_counter/_functions/is_main_guard.py
kdaquila_structure_lint/definition_counter/_functions/is_type_checking_guard.py
kdaquila_structure_lint-10.0.0.dist-info/METADATA
kdaquila_structure_lint-10.0.0.dist-info/WHEEL
kdaquila_structure_lint-10.0.0.dist-info/entry_points.txt
kdaquila_structure_lint-10.0.0.dist-info/licenses/LICENSE
kdaquila_structure_lint-10.0.0.dist-info/RECORD
