Metadata-Version: 2.4
Name: kdaquila-structure-lint
Version: 10.0.0
Summary: Opinionated Python project structure and code quality linter
Project-URL: Homepage, https://github.com/kdaquila/kdaquila-structure-lint
Project-URL: Repository, https://github.com/kdaquila/kdaquila-structure-lint
Project-URL: Issues, https://github.com/kdaquila/kdaquila-structure-lint/issues
Author-email: kdaquila <kfd182@gmail.com>
License: MIT License
License-File: LICENSE
Keywords: code-quality,linter,project-structure,structure,validation
Classifier: Development Status :: 3 - Alpha
Classifier: Intended Audience :: Developers
Classifier: License :: OSI Approved :: MIT License
Classifier: Programming Language :: Python :: 3
Classifier: Programming Language :: Python :: 3.10
Classifier: Programming Language :: Python :: 3.11
Classifier: Programming Language :: Python :: 3.12
Classifier: Programming Language :: Python :: 3.13
Classifier: Topic :: Software Development :: Quality Assurance
Requires-Python: >=3.10
Requires-Dist: tomli>=2.0.0; python_version < '3.11'
Requires-Dist: tree-sitter-python>=0.21.0
Requires-Dist: tree-sitter-typescript>=0.21.0
Requires-Dist: tree-sitter>=0.21.0
Provides-Extra: dev
Requires-Dist: mypy>=1.8.0; extra == 'dev'
Requires-Dist: pytest>=8.0.0; extra == 'dev'
Requires-Dist: ruff>=0.3.0; extra == 'dev'
